todo_mcp/__init__.py
todo_mcp/__main__.py
todo_mcp/config.py
todo_mcp/fastmcp_server.py
todo_mcp/http_server.py
todo_mcp/server.py
todo_mcp/models/__init__.py
todo_mcp/models/filters.py
todo_mcp/models/status.py
todo_mcp/models/task.py
todo_mcp/models/tool_call.py
todo_mcp/services/__init__.py
todo_mcp/services/hierarchy_service.py
todo_mcp/services/task_service.py
todo_mcp/static/index.html
todo_mcp/storage/__init__.py
todo_mcp/storage/file_manager.py
todo_mcp/storage/markdown_parser.py
todo_mcp/storage/markdown_writer.py
todo_mcp/tools/__init__.py
todo_mcp/tools/hierarchy_tools.py
todo_mcp/tools/query_tools.py
todo_mcp/tools/status_tools.py
todo_mcp/tools/task_tools.py
todo_mcp/utils/__init__.py
todo_mcp/utils/cache.py
todo_mcp/utils/date_utils.py
todo_mcp/utils/indexing.py
todo_mcp/utils/markdown_utils.py
todo_mcp/utils/validators.py
llm_todo_mcp_mao-0.1.1.dist-info/METADATA
llm_todo_mcp_mao-0.1.1.dist-info/WHEEL
llm_todo_mcp_mao-0.1.1.dist-info/entry_points.txt
llm_todo_mcp_mao-0.1.1.dist-info/RECORD
